{
  "irrcv": {
    "id": "irctlr",
    "pin": 34
  },
  "irled": [
    {
      "id": "irled",
      "pin": 4
    }
  ],
  "indicator": [
    {
      "id": "indicator",
      "pinR": 2,
      "pinG": 12,
      "pinB": 15
    }
  ],
  "lamp": [{ "id": "lamp", "pin": 13 }],
  "fan": [
    {
      "id": "fan",
      "pinSpd1": 25,
      "pinSpd2": 33,
      "pinDir1": 26,
      "pinDir2": 27
    }
  ],
  "switch": [
    { "id": "sw1", "pin": 23, "switched": [{ "id": "lamp" }] },
    { "id": "sw2", "pin": 19, "switched": [{ "id": "lamp" }] },
    { "id": "ir1", "ir": "ff609f", "switched": [{ "id": "lamp" }] },
    {
      "id": "irfan+",
      "ir": "ffe01f",
      "switched": [{ "id": "fan", "parm": "+" }]
    },
    {
      "id": "irfan-",
      "ir": "ff58a7",
      "switched": [{ "id": "fan", "parm": "-" }]
    },
    {
      "id": "irfan_pwr",
      "ir": "ff20df",
      "switched": [{ "id": "fan", "parm": "pwr" }]
    },
    {
      "id": "irfan_rev",
      "ir": "ff10ef",
      "switched": [{ "id": "fan", "parm": "rev" }]
    }
  ],
  "ldr": [
    {
      "id": "ldr",
      "pin": 35
    }
  ],
  "bme": [
    {
      "id": "bme",
      "addr": "0x76"
    }
  ]
}

